chip/ChipBluezMgr.py
chip/ChipCoreBluetoothMgr.py
chip/ChipReplStartup.py
home_assistant_chip_repl-2025.7.0.data/scripts/chip-repl
home_assistant_chip_repl-2025.7.0.dist-info/LICENSE
home_assistant_chip_repl-2025.7.0.dist-info/METADATA
home_assistant_chip_repl-2025.7.0.dist-info/WHEEL
home_assistant_chip_repl-2025.7.0.dist-info/top_level.txt
home_assistant_chip_repl-2025.7.0.dist-info/RECORD
