Metadata-Version: 2.1
Name: home-assistant-chip-repl
Version: 2025.7.0
Summary: Python-base APIs and tools for CHIP.
Home-page: https://github.com/project-chip/connectedhomeip
License: Apache
Classifier: Intended Audience :: Developers
Classifier: License :: OSI Approved :: Apache Software License
Classifier: Programming Language :: Python :: 3.7
Classifier: Programming Language :: Python :: 3.8
Classifier: Programming Language :: Python :: 3.9
Requires-Python: >=3.7
License-File: LICENSE
Requires-Dist: coloredlogs
Requires-Dist: ipython!=8.1.0
Requires-Dist: rich
Requires-Dist: ipykernel
Requires-Dist: dbus-python==1.2.18
Requires-Dist: pygobject==3.50.0
